ppipa/__init__.py
ppipa/__version__.py
ppipa/freeipaserver.py
ppipa/freeipauser.py
ppipa-1.0.6.dist-info/LICENSE.txt
ppipa-1.0.6.dist-info/METADATA
ppipa-1.0.6.dist-info/WHEEL
ppipa-1.0.6.dist-info/top_level.txt
ppipa-1.0.6.dist-info/RECORD
