Metadata-Version: 2.1
Name: ppipa
Version: 1.0.6
Summary: PP's FreeIPA Module
Home-page: https://github.com/peterpakos/ppipa
Author: Peter Pakos
Author-email: peter.pakos@wandisco.com
License: GPLv3
Keywords: ldap freeipa
Platform: UNKNOWN
Classifier: Programming Language :: Python :: 2
Classifier: Programming Language :: Python :: 2.7
Classifier: Programming Language :: Python :: 3
Classifier: Programming Language :: Python :: 3.4
Classifier: Programming Language :: Python :: 3.5
Classifier: Programming Language :: Python :: 3.6
Classifier: Programming Language :: Python :: 3.7
Classifier: License :: OSI Approved :: GNU General Public License v3 (GPLv3)
Classifier: Topic :: System :: Systems Administration :: Authentication/Directory :: LDAP
Requires-Dist: python-ldap
Requires-Dist: unidecode
Requires-Dist: pplogger
